{"name": "ActiveMatches", "matches": [{"matchID": "777cb7ad-7e4d-4d54-a898-66158ec24042", "matchIDinofficial": "20220425MON3", "matchNum": "3", "matchDate": "2022-04-25+08:00", "matchDay": "MON", "coupon": {"couponID": "3", "couponShortName": "MON", "couponNameCH": "\u5468\u4e00\u8cfd\u4e8b", "couponNameEN": "Monday Matches"}, "league": {"leagueID": "90", "leagueShortName": "ACL", "leagueNameCH": "\u4e9e\u6d32\u806f\u8cfd\u51a0\u8ecd\u76c3", "leagueNameEN": "Asian Champions League"}, "homeTeam": {"teamID": "3080", "teamNameCH": "\u6e05\u840a\u806f", "teamNameEN": "Chiangrai Utd"}, "awayTeam": {"teamID": "556", "teamNameCH": "\u795e\u6236\u52dd\u5229\u8239", "teamNameEN": "Vissel Kobe"}, "matchStatus": "ResultIn", "matchTime": "2022-04-25T22:00:00+08:00", "accumulatedscore": [{"periodvalue": "FirstHalf", "periodstatus": "ResultFinal", "home": "0", "away": "0"}, {"periodvalue": "SecondHalf", "periodstatus": "ResultFinal", "home": "0", "away": "0"}], "cornerresult": "9", "hasWebTV": false, "hasOdds": true, "hasExtraTimePools": false, "results": {"OOE": "E", "FHA": "D", "FTS": "N", "CRS": "00:00", "HFT": "D:D", "TTG": "+0", "FCS": "00:00", "NTS1": "N", "HAD": "D"}, "definedPools": [], "inplayPools": []}, {"matchID": "63d873d8-e285-4d15-a277-11a64d6882e0", "matchIDinofficial": "20220425MON25", "matchNum": "25", "matchDate": "2022-04-25+08:00", "matchDay": "MON", "coupon": {"couponID": "3", "couponShortName": "MON", "couponNameCH": "\u5468\u4e00\u8cfd\u4e8b", "couponNameEN": "Monday Matches"}, "league": {"leagueID": "94", "leagueShortName": "APL", "leagueNameCH": "\u963f\u6839\u5ef7\u7532\u7d44\u806f\u8cfd", "leagueNameEN": "Argentine Division 1"}, "homeTeam": {"teamID": "1184", "teamNameCH": "\u5c0f\u963f\u6839\u5ef7\u4eba", "teamNameEN": "Argentinos Juniors"}, "awayTeam": {"teamID": "2505", "teamNameCH": "\u6c99\u7c73\u6069\u5716", "teamNameEN": "Sarmiento"}, "matchStatus": "ResultIn", "matchTime": "2022-04-26T08:30:00+08:00", "accumulatedscore": [{"periodvalue": "FirstHalf", "periodstatus": "ResultFinal", "home": "0", "away": "0"}, {"periodvalue": "SecondHalf", "periodstatus": "ResultFinal", "home": "0", "away": "0"}], "hasWebTV": false, "hasOdds": true, "hasExtraTimePools": false, "results": {"OOE": "E", "FHA": "D", "FTS": "N", "CRS": "00:00", "HFT": "D:D", "TTG": "+0", "FCS": "00:00", "HAD": "D"}, "definedPools": [], "inplayPools": []}, {"matchID": "ec0885b9-3711-4a0b-a838-084de49eca9c", "matchIDinofficial": "20220425MON13", "matchNum": "13", "matchDate": "2022-04-25+08:00", "matchDay": "MON", "coupon": {"couponID": "3", "couponShortName": "MON", "couponNameCH": "\u5468\u4e00\u8cfd\u4e8b", "couponNameEN": "Monday Matches"}, "league": {"leagueID": "104", "leagueShortName": "DF2", "leagueNameCH": "\u8377\u862d\u4e59\u7d44\u806f\u8cfd", "leagueNameEN": "Dutch Division 2"}, "homeTeam": {"teamID": "2127", "teamNameCH": "\u963f\u7a4d\u58eb\u9752\u5e74\u968a", "teamNameEN": "Jong Ajax"}, "awayTeam": {"teamID": "914", "teamNameCH": "\u82ac\u6d1b", "teamNameEN": "Venlo"}, "matchStatus": "ResultIn", "matchTime": "2022-04-26T02:00:00+08:00", "accumulatedscore": [{"periodvalue": "FirstHalf", "periodstatus": "ResultFinal", "home": "1", "away": "1"}, {"periodvalue": "SecondHalf", "periodstatus": "ResultFinal", "home": "6", "away": "1"}], "hasWebTV": false, "hasOdds": true, "hasExtraTimePools": false, "results": {"OOE": "O", "FHA": "D", "FTS": "H", "CRS": "-1:-H", "HFT": "D:H", "TTG": "-7", "FCS": "01:01", "HAD": "H"}, "definedPools": [], "inplayPools": []}, {"matchID": "ed396968-d282-437b-9835-cd6c443b3454", "matchIDinofficial": "20220425MON14", "matchNum": "14", "matchDate": "2022-04-25+08:00", "matchDay": "MON", "coupon": {"couponID": "3", "couponShortName": "MON", "couponNameCH": "\u5468\u4e00\u8cfd\u4e8b", "couponNameEN": "Monday Matches"}, "league": {"leagueID": "104", "leagueShortName": "DF2", "leagueNameCH": "\u8377\u862d\u4e59\u7d44\u806f\u8cfd", "leagueNameEN": "Dutch Division 2"}, "homeTeam": {"teamID": "2129", "teamNameCH": "\u71d5\u8c6a\u82ac\u9752\u5e74\u968a", "teamNameEN": "Jong PSV Eindhoven"}, "awayTeam": {"teamID": "794", "teamNameCH": "\u99ac\u65af\u7279\u91cc\u8d6b\u7279", "teamNameEN": "Maastricht"}, "matchStatus": "ResultIn", "matchTime": "2022-04-26T02:00:00+08:00", "accumulatedscore": [{"periodvalue": "FirstHalf", "periodstatus": "ResultFinal", "home": "2", "away": "0"}, {"periodvalue": "SecondHalf", "periodstatus": "ResultFinal", "home": "2", "away": "2"}], "hasWebTV": false, "hasOdds": true, "hasExtraTimePools": false, "results": {"OOE": "E", "FHA": "H", "FTS": "H", "HFT": "H:D", "CRS": "02:02", "TTG": "+4", "FCS": "02:00", "HAD": "D"}, "definedPools": [], "inplayPools": []}, {"matchID": "e6fdd5be-b67f-454d-acc7-f259c6a5019d", "matchIDinofficial": "20220425MON16", "matchNum": "16", "matchDate": "2022-04-25+08:00", "matchDay": "MON", "coupon": {"couponID": "3", "couponShortName": "MON", "couponNameCH": "\u5468\u4e00\u8cfd\u4e8b", "couponNameEN": "Monday Matches"}, "league": {"leagueID": "94", "leagueShortName": "APL", "leagueNameCH": "\u963f\u6839\u5ef7\u7532\u7d44\u806f\u8cfd", "leagueNameEN": "Argentine Division 1"}, "homeTeam": {"teamID": "1365", "teamNameCH": "\u5824\u683c\u96f7", "teamNameEN": "Tigre"}, "awayTeam": {"teamID": "1364", "teamNameCH": "\u6c99\u862d\u8fea\u5175\u5de5\u5ee0", "teamNameEN": "Sarandi Arsenal"}, "matchStatus": "ResultIn", "matchTime": "2022-04-26T02:30:00+08:00", "accumulatedscore": [{"periodvalue": "FirstHalf", "periodstatus": "ResultFinal", "home": "0", "away": "0"}, {"periodvalue": "SecondHalf", "periodstatus": "ResultFinal", "home": "0", "away": "0"}], "hasWebTV": false, "hasOdds": true, "hasExtraTimePools": false, "results": {"OOE": "E", "FHA": "D", "FTS": "N", "HFT": "D:D", "CRS": "00:00", "TTG": "+0", "FCS": "00:00", "HAD": "D"}, "definedPools": [], "inplayPools": []}, {"matchID": "eb5c608a-01dd-4cc1-b58f-431243936ff7", "matchIDinofficial": "20220425MON2", "matchNum": "2", "matchDate": "2022-04-25+08:00", "matchDay": "MON", "coupon": {"couponID": "3", "couponShortName": "MON", "couponNameCH": "\u5468\u4e00\u8cfd\u4e8b", "couponNameEN": "Monday Matches"}, "league": {"leagueID": "90", "leagueShortName": "ACL", "leagueNameCH": "\u4e9e\u6d32\u806f\u8cfd\u51a0\u8ecd\u76c3", "leagueNameEN": "Asian Champions League"}, "homeTeam": {"teamID": "557", "teamNameCH": "\u6a6b\u6ff1\u6c34\u624b", "teamNameEN": "Yokohama F.Marinos"}, "awayTeam": {"teamID": "1085", "teamNameCH": "FC\u6089\u5c3c", "teamNameEN": "Sydney FC"}, "matchStatus": "ResultIn", "matchTime": "2022-04-25T19:00:00+08:00", "accumulatedscore": [{"periodvalue": "FirstHalf", "periodstatus": "ResultFinal", "home": "2", "away": "0"}, {"periodvalue": "SecondHalf", "periodstatus": "ResultFinal", "home": "3", "away": "0"}], "cornerresult": "10", "hasWebTV": false, "hasOdds": true, "hasExtraTimePools": false, "results": {"OOE": "O", "NTS3": "H", "FHA": "H", "FTS": "H", "NTS2": "H", "CRS": "03:00", "HFT": "H:H", "TTG": "+3", "FCS": "02:00", "NTS4": "N", "NTS1": "H", "HAD": "H"}, "definedPools": [], "inplayPools": []}, {"matchID": "12b338e8-a119-4638-8c37-148a46026dbc", "matchIDinofficial": "20220425MON1", "matchNum": "1", "matchDate": "2022-04-25+08:00", "matchDay": "MON", "coupon": {"couponID": "3", "couponShortName": "MON", "couponNameCH": "\u5468\u4e00\u8cfd\u4e8b", "couponNameEN": "Monday Matches"}, "league": {"leagueID": "89", "leagueShortName": "AD1", "leagueNameCH": "\u6fb3\u6d32\u8077\u696d\u806f\u8cfd", "leagueNameEN": "Australian Division 1"}, "homeTeam": {"teamID": "1156", "teamNameCH": "\u5e03\u91cc\u65af\u73ed\u7345\u543c", "teamNameEN": "Brisbane Roar"}, "awayTeam": {"teamID": "1095", "teamNameCH": "\u58a8\u723e\u672c\u52dd\u5229", "teamNameEN": "Melbourne Victory"}, "matchStatus": "ResultIn", "matchTime": "2022-04-25T12:05:00+08:00", "accumulatedscore": [{"periodvalue": "FirstHalf", "periodstatus": "ResultFinal", "home": "0", "away": "0"}, {"periodvalue": "SecondHalf", "periodstatus": "ResultFinal", "home": "1", "away": "1"}], "cornerresult": "12", "hasWebTV": false, "hasOdds": true, "hasExtraTimePools": false, "results": {"OOE": "E", "NTS3": "N", "FHA": "D", "FTS": "H", "NTS2": "A", "HFT": "D:D", "CRS": "01:01", "TTG": "+2", "FCS": "00:00", "NTS1": "H", "HAD": "D"}, "definedPools": [], "inplayPools": []}, {"matchID": "08d3652c-c487-43b6-baf0-9b03bcb17e4f", "matchIDinofficial": "20220425MON21", "matchNum": "21", "matchDate": "2022-04-25+08:00", "matchDay": "MON", "coupon": {"couponID": "3", "couponShortName": "MON", "couponNameCH": "\u5468\u4e00\u8cfd\u4e8b", "couponNameEN": "Monday Matches"}, "league": {"leagueID": "152", "leagueShortName": "SF2", "leagueNameCH": "\u897f\u73ed\u7259\u4e59\u7d44\u806f\u8cfd", "leagueNameEN": "Spanish Division 2"}, "homeTeam": {"teamID": "973", "teamNameCH": "\u827e\u7f8e\u5229\u4e9e", "teamNameEN": "Almeria"}, "awayTeam": {"teamID": "1161", "teamNameCH": "\u5e0c\u676d", "teamNameEN": "Gijon"}, "matchStatus": "ResultIn", "matchTime": "2022-04-26T03:00:00+08:00", "accumulatedscore": [{"periodvalue": "FirstHalf", "periodstatus": "ResultFinal", "home": "0", "away": "0"}, {"periodvalue": "SecondHalf", "periodstatus": "ResultFinal", "home": "1", "away": "0"}], "hasWebTV": false, "hasOdds": true, "hasExtraTimePools": false, "results": {"OOE": "O", "FHA": "D", "FTS": "H", "CRS": "01:00", "HFT": "D:H", "TTG": "+1", "FCS": "00:00", "HAD": "H"}, "definedPools": [], "inplayPools": []}, {"matchID": "644ecac7-ac74-443f-9b20-4cbd0456a14c", "matchIDinofficial": "20220426TUE4", "matchNum": "4", "matchDate": "2022-04-26+08:00", "matchDay": "TUE", "coupon": {"couponID": "4", "couponShortName": "TUE", "couponNameCH": "\u5468\u4e8c\u8cfd\u4e8b", "couponNameEN": "Tuesday Matches"}, "league": {"leagueID": "90", "leagueShortName": "ACL", "leagueNameCH": "\u4e9e\u6d32\u806f\u8cfd\u51a0\u8ecd\u76c3", "leagueNameEN": "Asian Champions League"}, "homeTeam": {"teamID": "1842", "teamNameCH": "\u827e\u675c\u54c8\u5c3c", "teamNameEN": "Al Duhail"}, "awayTeam": {"teamID": "1020", "teamNameCH": "\u6c99\u5df4\u7f55", "teamNameEN": "Sepahan"}, "matchStatus": "ResultIn", "matchTime": "2022-04-27T01:15:00+08:00", "accumulatedscore": [{"periodvalue": "FirstHalf", "periodstatus": "ResultFinal", "home": "3", "away": "1"}], "cornerresult": "-", "hasWebTV": false, "hasOdds": true, "hasExtraTimePools": false, "results": {"OOE": "-", "NTS3": "H", "FHA": "H", "FTS": "H", "NTS2": "A", "HFT": "-", "CRS": "-", "TTG": "-", "NTS5": "-", "FCS": "03:01", "NTS4": "H", "NTS1": "H", "HAD": "-"}, "definedPools": [], "inplayPools": []}, {"matchID": "90eeae82-c970-4a07-8169-9b0c5cb70e9c", "matchIDinofficial": "20220425MON17", "matchNum": "17", "matchDate": "2022-04-25+08:00", "matchDay": "MON", "coupon": {"couponID": "3", "couponShortName": "MON", "couponNameCH": "\u5468\u4e00\u8cfd\u4e8b", "couponNameEN": "Monday Matches"}, "league": {"leagueID": "2", "leagueShortName": "ISA", "leagueNameCH": "\u610f\u5927\u5229\u7532\u7d44\u806f\u8cfd", "leagueNameEN": "Italian Division 1"}, "homeTeam": {"teamID": "1509", "teamNameCH": "\u85a9\u65af\u7d22\u7f85", "teamNameEN": "Sassuolo"}, "awayTeam": {"teamID": "46", "teamNameCH": "\u7956\u96f2\u9054\u65af", "teamNameEN": "Juventus"}, "matchStatus": "ResultIn", "matchTime": "2022-04-26T02:45:00+08:00", "accumulatedscore": [{"periodvalue": "FirstHalf", "periodstatus": "ResultFinal", "home": "1", "away": "1"}, {"periodvalue": "SecondHalf", "periodstatus": "ResultFinal", "home": "1", "away": "2"}], "cornerresult": "10", "hasWebTV": false, "hasOdds": true, "hasExtraTimePools": false, "results": {"OOE": "O", "NTS3": "A", "FHA": "D", "FTS": "H", "NTS2": "A", "CRS": "01:02", "HFT": "D:A", "TTG": "+3", "FCS": "01:01", "NTS4": "N", "NTS1": "H", "HAD": "A"}, "definedPools": [], "inplayPools": []}, {"matchID": "66539a44-86e6-4692-bb2b-d03b0802a985", "matchIDinofficial": "20220425MON8", "matchNum": "8", "matchDate": "2022-04-25+08:00", "matchDay": "MON", "coupon": {"couponID": "3", "couponShortName": "MON", "couponNameCH": "\u5468\u4e00\u8cfd\u4e8b", "couponNameEN": "Monday Matches"}, "league": {"leagueID": "17", "leagueShortName": "PFL", "leagueNameCH": "\u8461\u8404\u7259\u8d85\u7d1a\u806f\u8cfd", "leagueNameEN": "Portuguese Premier"}, "homeTeam": {"teamID": "292", "teamNameCH": "\u5e03\u62c9\u52a0", "teamNameEN": "Braga"}, "awayTeam": {"teamID": "99", "teamNameCH": "\u6ce2\u5716", "teamNameEN": "Porto"}, "matchStatus": "ResultIn", "matchTime": "2022-04-26T01:00:00+08:00", "accumulatedscore": [{"periodvalue": "FirstHalf", "periodstatus": "ResultFinal", "home": "0", "away": "0"}, {"periodvalue": "SecondHalf", "periodstatus": "ResultFinal", "home": "1", "away": "0"}], "hasWebTV": false, "hasOdds": true, "hasExtraTimePools": false, "results": {"OOE": "O", "FHA": "D", "FTS": "H", "CRS": "01:00", "HFT": "D:H", "TTG": "+1", "FCS": "00:00", "HAD": "H"}, "definedPools": [], "inplayPools": []}, {"matchID": "1a4b78a0-c819-4852-9e16-217da4187b54", "matchIDinofficial": "20220425MON10", "matchNum": "10", "matchDate": "2022-04-25+08:00", "matchDay": "MON", "coupon": {"couponID": "3", "couponShortName": "MON", "couponNameCH": "\u5468\u4e00\u8cfd\u4e8b", "couponNameEN": "Monday Matches"}, "league": {"leagueID": "58", "leagueShortName": "SAL", "leagueNameCH": "\u745e\u5178\u8d85\u7d1a\u806f\u8cfd", "leagueNameEN": "Swedish Division 1"}, "homeTeam": {"teamID": "2259", "teamNameCH": "\u5929\u72fc\u661f", "teamNameEN": "Sirius"}, "awayTeam": {"teamID": "411", "teamNameCH": "\u54c8\u99ac\u6bd4", "teamNameEN": "Hammarby"}, "matchStatus": "ResultIn", "matchTime": "2022-04-26T01:00:00+08:00", "accumulatedscore": [{"periodvalue": "FirstHalf", "periodstatus": "ResultFinal", "home": "0", "away": "1"}, {"periodvalue": "SecondHalf", "periodstatus": "ResultFinal", "home": "0", "away": "3"}], "hasWebTV": false, "hasOdds": true, "hasExtraTimePools": false, "results": {"OOE": "O", "FHA": "A", "FTS": "A", "CRS": "00:03", "HFT": "A:A", "TTG": "+3", "FCS": "00:01", "HAD": "A"}, "definedPools": [], "inplayPools": []}, {"matchID": "a6cc00b6-e4cc-4b5d-bb75-1ad2c4d2b42b", "matchIDinofficial": "20220425MON12", "matchNum": "12", "matchDate": "2022-04-25+08:00", "matchDay": "MON", "coupon": {"couponID": "3", "couponShortName": "MON", "couponNameCH": "\u5468\u4e00\u8cfd\u4e8b", "couponNameEN": "Monday Matches"}, "league": {"leagueID": "58", "leagueShortName": "SAL", "leagueNameCH": "\u745e\u5178\u8d85\u7d1a\u806f\u8cfd", "leagueNameEN": "Swedish Division 1"}, "homeTeam": {"teamID": "601", "teamNameCH": "\u99ac\u6a21", "teamNameEN": "Malmo"}, "awayTeam": {"teamID": "595", "teamNameCH": "\u54e5\u767b\u5821", "teamNameEN": "Goteborg"}, "matchStatus": "ResultIn", "matchTime": "2022-04-26T01:10:00+08:00", "accumulatedscore": [{"periodvalue": "FirstHalf", "periodstatus": "ResultFinal", "home": "0", "away": "0"}, {"periodvalue": "SecondHalf", "periodstatus": "ResultFinal", "home": "1", "away": "0"}], "cornerresult": "7", "hasWebTV": false, "hasOdds": true, "hasExtraTimePools": false, "results": {"OOE": "O", "FHA": "D", "FTS": "H", "NTS2": "N", "CRS": "01:00", "HFT": "D:H", "TTG": "+1", "FCS": "00:00", "NTS1": "H", "HAD": "H"}, "definedPools": [], "inplayPools": []}, {"matchID": "8ef44bd8-fc8b-4930-a46f-74688b44b85b", "matchIDinofficial": "20220425MON24", "matchNum": "24", "matchDate": "2022-04-25+08:00", "matchDay": "MON", "coupon": {"couponID": "3", "couponShortName": "MON", "couponNameCH": "\u5468\u4e00\u8cfd\u4e8b", "couponNameEN": "Monday Matches"}, "league": {"leagueID": "94", "leagueShortName": "APL", "leagueNameCH": "\u963f\u6839\u5ef7\u7532\u7d44\u806f\u8cfd", "leagueNameEN": "Argentine Division 1"}, "homeTeam": {"teamID": "2502", "teamNameCH": "\u963f\u5ea6\u65af\u7dad", "teamNameEN": "Aldosivi"}, "awayTeam": {"teamID": "1360", "teamNameCH": "\u98b6\u98a8\u968a", "teamNameEN": "Huracan"}, "matchStatus": "ResultIn", "matchTime": "2022-04-26T08:30:00+08:00", "accumulatedscore": [{"periodvalue": "FirstHalf", "periodstatus": "ResultFinal", "home": "0", "away": "2"}, {"periodvalue": "SecondHalf", "periodstatus": "ResultFinal", "home": "0", "away": "2"}], "hasWebTV": false, "hasOdds": true, "hasExtraTimePools": false, "results": {"OOE": "E", "FHA": "A", "FTS": "A", "CRS": "00:02", "HFT": "A:A", "TTG": "+2", "FCS": "00:02", "HAD": "A"}, "definedPools": [], "inplayPools": []}, {"matchID": "e2fe6b8d-e051-4366-9380-d94653298e11", "matchIDinofficial": "20220425MON11", "matchNum": "11", "matchDate": "2022-04-25+08:00", "matchDay": "MON", "coupon": {"couponID": "3", "couponShortName": "MON", "couponNameCH": "\u5468\u4e00\u8cfd\u4e8b", "couponNameEN": "Monday Matches"}, "league": {"leagueID": "58", "leagueShortName": "SAL", "leagueNameCH": "\u745e\u5178\u8d85\u7d1a\u806f\u8cfd", "leagueNameEN": "Swedish Division 1"}, "homeTeam": {"teamID": "1596", "teamNameCH": "\u83ef\u7d0d\u83ab", "teamNameEN": "Varnamo"}, "awayTeam": {"teamID": "1128", "teamNameCH": "\u8fea\u52a0\u79d1\u65af", "teamNameEN": "Degerfors"}, "matchStatus": "ResultIn", "matchTime": "2022-04-26T01:00:00+08:00", "accumulatedscore": [{"periodvalue": "FirstHalf", "periodstatus": "ResultFinal", "home": "1", "away": "0"}, {"periodvalue": "SecondHalf", "periodstatus": "ResultFinal", "home": "2", "away": "0"}], "hasWebTV": false, "hasOdds": true, "hasExtraTimePools": false, "results": {"OOE": "E", "FHA": "H", "FTS": "H", "CRS": "02:00", "HFT": "H:H", "TTG": "+2", "FCS": "01:00", "HAD": "H"}, "definedPools": [], "inplayPools": []}, {"matchID": "b1f97e1e-776d-4534-b19b-98e02fc71262", "matchIDinofficial": "20220425MON4", "matchNum": "4", "matchDate": "2022-04-25+08:00", "matchDay": "MON", "coupon": {"couponID": "3", "couponShortName": "MON", "couponNameCH": "\u5468\u4e00\u8cfd\u4e8b", "couponNameEN": "Monday Matches"}, "league": {"leagueID": "90", "leagueShortName": "ACL", "leagueNameCH": "\u4e9e\u6d32\u806f\u8cfd\u51a0\u8ecd\u76c3", "leagueNameEN": "Asian Champions League"}, "homeTeam": {"teamID": "3485", "teamNameCH": "HA\u5609\u840a", "teamNameEN": "HA Gia Lai"}, "awayTeam": {"teamID": "874", "teamNameCH": "\u5168\u5317\u6c7d\u8eca", "teamNameEN": "Jeonbuk Motors"}, "matchStatus": "ResultIn", "matchTime": "2022-04-25T22:00:00+08:00", "accumulatedscore": [{"periodvalue": "FirstHalf", "periodstatus": "ResultFinal", "home": "0", "away": "1"}, {"periodvalue": "SecondHalf", "periodstatus": "ResultFinal", "home": "1", "away": "1"}], "hasWebTV": false, "hasOdds": true, "hasExtraTimePools": false, "results": {"OOE": "E", "FHA": "A", "FTS": "A", "HFT": "A:D", "CRS": "01:01", "TTG": "+2", "FCS": "00:01", "HAD": "D"}, "definedPools": [], "inplayPools": []}, {"matchID": "6775719d-7f0c-47f7-a20b-32955785ed28", "matchIDinofficial": "20220425MON19", "matchNum": "19", "matchDate": "2022-04-25+08:00", "matchDay": "MON", "coupon": {"couponID": "3", "couponShortName": "MON", "couponNameCH": "\u5468\u4e00\u8cfd\u4e8b", "couponNameEN": "Monday Matches"}, "league": {"leagueID": "1", "leagueShortName": "EPL", "leagueNameCH": "\u82f1\u683c\u862d\u8d85\u7d1a\u806f\u8cfd", "leagueNameEN": "Eng Premier"}, "homeTeam": {"teamID": "194", "teamNameCH": "\u6c34\u6676\u5bae", "teamNameEN": "Crystal Palace"}, "awayTeam": {"teamID": "10", "teamNameCH": "\u5217\u65af\u806f", "teamNameEN": "Leeds"}, "matchStatus": "ResultIn", "matchTime": "2022-04-26T03:00:00+08:00", "accumulatedscore": [{"periodvalue": "FirstHalf", "periodstatus": "ResultFinal", "home": "0", "away": "0"}, {"periodvalue": "SecondHalf", "periodstatus": "ResultFinal", "home": "0", "away": "0"}], "cornerresult": "9", "hasWebTV": false, "hasOdds": true, "hasExtraTimePools": false, "results": {"OOE": "E", "FHA": "D", "FTS": "N", "CRS": "00:00", "HFT": "D:D", "TTG": "+0", "FCS": "00:00", "NTS1": "N", "HAD": "D"}, "definedPools": [], "inplayPools": []}, {"matchID": "366e0ba4-b921-4940-b55e-e039b102e712", "matchIDinofficial": "20220425MON9", "matchNum": "9", "matchDate": "2022-04-25+08:00", "matchDay": "MON", "coupon": {"couponID": "3", "couponShortName": "MON", "couponNameCH": "\u5468\u4e00\u8cfd\u4e8b", "couponNameEN": "Monday Matches"}, "league": {"leagueID": "58", "leagueShortName": "SAL", "leagueNameCH": "\u745e\u5178\u8d85\u7d1a\u806f\u8cfd", "leagueNameEN": "Swedish Division 1"}, "homeTeam": {"teamID": "603", "teamNameCH": "\u827e\u592b\u65af\u5821", "teamNameEN": "Elfsborg"}, "awayTeam": {"teamID": "593", "teamNameCH": "\u8f9b\u65af\u83ef\u723e", "teamNameEN": "Sundsvall"}, "matchStatus": "ResultIn", "matchTime": "2022-04-26T01:00:00+08:00", "accumulatedscore": [{"periodvalue": "FirstHalf", "periodstatus": "ResultFinal", "home": "1", "away": "1"}, {"periodvalue": "SecondHalf", "periodstatus": "ResultFinal", "home": "3", "away": "1"}], "hasWebTV": false, "hasOdds": true, "hasExtraTimePools": false, "results": {"OOE": "E", "FHA": "D", "FTS": "H", "CRS": "03:01", "HFT": "D:H", "TTG": "+4", "FCS": "01:01", "HAD": "H"}, "definedPools": [], "inplayPools": []}, {"matchID": "777a4c65-7347-4a77-b184-91c60fbeccd4", "matchIDinofficial": "20220425MON15", "matchNum": "15", "matchDate": "2022-04-25+08:00", "matchDay": "MON", "coupon": {"couponID": "3", "couponShortName": "MON", "couponNameCH": "\u5468\u4e00\u8cfd\u4e8b", "couponNameEN": "Monday Matches"}, "league": {"leagueID": "29", "leagueShortName": "ED1", "leagueNameCH": "\u82f1\u683c\u862d\u51a0\u8ecd\u806f\u8cfd", "leagueNameEN": "Eng Championship"}, "homeTeam": {"teamID": "201", "teamNameCH": "\u666e\u96f7\u65af\u9813", "teamNameEN": "Preston"}, "awayTeam": {"teamID": "4", "teamNameCH": "\u5e03\u529b\u822c\u6d41\u6d6a", "teamNameEN": "Blackburn"}, "matchStatus": "ResultIn", "matchTime": "2022-04-26T02:30:00+08:00", "accumulatedscore": [{"periodvalue": "FirstHalf", "periodstatus": "ResultFinal", "home": "1", "away": "3"}, {"periodvalue": "SecondHalf", "periodstatus": "ResultFinal", "home": "1", "away": "4"}], "hasWebTV": false, "hasOdds": true, "hasExtraTimePools": false, "results": {"OOE": "O", "FHA": "A", "FTS": "A", "CRS": "01:04", "HFT": "A:A", "TTG": "+5", "FCS": "01:03", "HAD": "A"}, "definedPools": [], "inplayPools": []}, {"matchID": "fdc2621c-77f1-4465-989d-fbe010368a66", "matchIDinofficial": "20220425MON18", "matchNum": "18", "matchDate": "2022-04-25+08:00", "matchDay": "MON", "coupon": {"couponID": "3", "couponShortName": "MON", "couponNameCH": "\u5468\u4e00\u8cfd\u4e8b", "couponNameEN": "Monday Matches"}, "league": {"leagueID": "103", "leagueShortName": "FF2", "leagueNameCH": "\u6cd5\u570b\u4e59\u7d44\u806f\u8cfd", "leagueNameEN": "French Division 2"}, "homeTeam": {"teamID": "222", "teamNameCH": "\u5716\u76e7\u8332", "teamNameEN": "Toulouse"}, "awayTeam": {"teamID": "881", "teamNameCH": "\u5c3c\u5967\u7279", "teamNameEN": "Niort"}, "matchStatus": "ResultIn", "matchTime": "2022-04-26T02:45:00+08:00", "accumulatedscore": [{"periodvalue": "FirstHalf", "periodstatus": "ResultFinal", "home": "1", "away": "0"}, {"periodvalue": "SecondHalf", "periodstatus": "ResultFinal", "home": "2", "away": "0"}], "hasWebTV": false, "hasOdds": true, "hasExtraTimePools": false, "results": {"OOE": "E", "FHA": "H", "FTS": "H", "CRS": "02:00", "HFT": "H:H", "TTG": "+2", "FCS": "01:00", "HAD": "H"}, "definedPools": [], "inplayPools": []}, {"matchID": "d09127d4-c8ac-4245-bbb0-cd7e4749baf2", "matchIDinofficial": "20220425MON22", "matchNum": "22", "matchDate": "2022-04-25+08:00", "matchDay": "MON", "coupon": {"couponID": "3", "couponShortName": "MON", "couponNameCH": "\u5468\u4e00\u8cfd\u4e8b", "couponNameEN": "Monday Matches"}, "league": {"leagueID": "17", "leagueShortName": "PFL", "leagueNameCH": "\u8461\u8404\u7259\u8d85\u7d1a\u806f\u8cfd", "leagueNameEN": "Portuguese Premier"}, "homeTeam": {"teamID": "246", "teamNameCH": "\u535a\u7dad\u65af\u5854", "teamNameEN": "Boavista"}, "awayTeam": {"teamID": "265", "teamNameCH": "\u58eb\u7835\u4ead", "teamNameEN": "Sporting"}, "matchStatus": "ResultIn", "matchTime": "2022-04-26T03:30:00+08:00", "accumulatedscore": [{"periodvalue": "FirstHalf", "periodstatus": "ResultFinal", "home": "0", "away": "1"}, {"periodvalue": "SecondHalf", "periodstatus": "ResultFinal", "home": "0", "away": "3"}], "hasWebTV": false, "hasOdds": true, "hasExtraTimePools": false, "results": {"OOE": "O", "FHA": "A", "FTS": "A", "CRS": "00:03", "HFT": "A:A", "TTG": "+3", "FCS": "00:01", "HAD": "A"}, "definedPools": [], "inplayPools": []}, {"matchID": "fa4ed02d-b1ac-4666-a6ca-2ef03f67c5e6", "matchIDinofficial": "20220425MON23", "matchNum": "23", "matchDate": "2022-04-25+08:00", "matchDay": "MON", "coupon": {"couponID": "3", "couponShortName": "MON", "couponNameCH": "\u5468\u4e00\u8cfd\u4e8b", "couponNameEN": "Monday Matches"}, "league": {"leagueID": "56", "leagueShortName": "BD1", "leagueNameCH": "\u5df4\u897f\u7532\u7d44\u806f\u8cfd", "leagueNameEN": "Brazilian Division 1"}, "homeTeam": {"teamID": "1245", "teamNameCH": "\u827e\u83ef\u723e", "teamNameEN": "Avai"}, "awayTeam": {"teamID": "569", "teamNameCH": "\u6208\u4e9e\u65af", "teamNameEN": "Goias"}, "matchStatus": "ResultIn", "matchTime": "2022-04-26T07:00:00+08:00", "accumulatedscore": [{"periodvalue": "FirstHalf", "periodstatus": "ResultFinal", "home": "1", "away": "0"}, {"periodvalue": "SecondHalf", "periodstatus": "ResultFinal", "home": "3", "away": "2"}], "cornerresult": "8", "hasWebTV": false, "hasOdds": true, "hasExtraTimePools": false, "results": {"OOE": "O", "NTS3": "H", "FHA": "H", "FTS": "H", "NTS2": "H", "CRS": "03:02", "HFT": "H:H", "TTG": "+5", "NTS5": "A", "FCS": "01:00", "NTS4": "A", "NTS1": "H", "NTS6": "N", "HAD": "H"}, "definedPools": [], "inplayPools": []}]}